{"initial_view":1,"mesh":[{"n":"skybox","p":0,"i":0},{"n":"tile","p":0,"i":1},{"n":"mine","p":0,"i":2},{"n":"rect","p":0,"i":3},{"n":"box","p":0,"i":4},{"n":"reticle","p":0,"i":5},{"n":"debug_grid","p":0,"i":6}],"texture":[{"n":"icon","p":0,"i":0},{"n":"tile","p":0,"i":1},{"n":"mine","p":0,"i":2},{"n":"tex-counter","p":0,"i":3},{"n":"tex-newgame","p":0,"i":4},{"n":"tex-loadgame","p":0,"i":5}],"shader":[{"n":"mesh_pc","p":0,"i":0},{"n":"mesh_pt","p":0,"i":1}],"draw":[{"n":"skybox","p":0,"i":0},{"n":"ui-rect","p":0,"i":1},{"n":"tile","p":0,"i":2},{"n":"mine","p":0,"i":3},{"n":"ui-counter","p":0,"i":4},{"n":"ui-newgame","p":0,"i":5},{"n":"ui-loadgame","p":0,"i":6}],"item":[{"n":"pick","p":0,"i":0}],"tile":[{"n":"tile","p":0,"i":0,"sid":1},{"n":"mine","p":0,"i":1,"sid":2}],"ui":[{"n":"counter","p":0,"i":0},{"n":"left-stick","p":0,"i":1},{"n":"right-stick","p":0,"i":2},{"n":"button-escape","p":0,"i":3},{"n":"button-newgame","p":0,"i":4},{"n":"button-loadgame","p":0,"i":5}],"event":[{"n":"update-counter","p":0,"i":0},{"n":"movement","p":0,"i":1},{"n":"escape","p":0,"i":2},{"n":"newgame","p":0,"i":3},{"n":"loadgame","p":0,"i":4}],"view":[{"n":"main","p":0,"i":0},{"n":"pause","p":0,"i":1}]}